sen2like_processor_bindings/__init__.py
sen2like_processor_bindings/model.py
eodc_faas_sen2like-2025.11.1.dist-info/METADATA
eodc_faas_sen2like-2025.11.1.dist-info/WHEEL
eodc_faas_sen2like-2025.11.1.dist-info/RECORD
