Metadata-Version: 2.1
Name: eodc-faas-sen2like
Version: 2025.11.1
Summary: Bindings for the sen2like processor exposed at EODC
Author: Valentina Hutter
Author-email: valentina.hutter@eodc.eu
Requires-Python: >=3.10,<3.12
Classifier: Programming Language :: Python :: 3
Classifier: Programming Language :: Python :: 3.10
Classifier: Programming Language :: Python :: 3.11
Requires-Dist: pydantic (>=2.0.1,<3.0.0)
Requires-Dist: pyproj (>=3.6.0,<4.0.0)
